{
  "jeremiah-smith": {
    "name": "Jeremiah Smith",
    "position": "WR",
    "college": "Ohio State",
    "projection": "Top-5",
    "ranking_overall": 1
  },
  "arch-manning": {
    "name": "Arch Manning",
    "position": "QB",
    "college": "Texas",
    "projection": "Top-5",
    "ranking_overall": 2
  },
  "dante-moore": {
    "name": "Dante Moore",
    "position": "QB",
    "college": "Oregon",
    "projection": "Top-5",
    "ranking_overall": 3
  },
  "colin-simmons": {
    "name": "Colin Simmons",
    "position": "EDGE",
    "college": "Texas",
    "projection": "Top-5",
    "ranking_overall": 4
  },
  "julian-sayin": {
    "name": "Julian Sayin",
    "position": "QB",
    "college": "Ohio State",
    "projection": "Top-10",
    "ranking_overall": 5
  },
  "dylan-stewart": {
    "name": "Dylan Stewart",
    "position": "EDGE",
    "college": "South Carolina",
    "projection": "Top-10",
    "ranking_overall": 6
  },
  "leonard-moore": {
    "name": "Leonard Moore",
    "position": "CB",
    "college": "Notre Dame",
    "projection": "Top-10",
    "ranking_overall": 7
  },
  "cam-coleman": {
    "name": "Cam Coleman",
    "position": "WR",
    "college": "Texas",
    "projection": "Top-10",
    "ranking_overall": 8
  },
  "jordan-seaton": {
    "name": "Jordan Seaton",
    "position": "OT",
    "college": "LSU",
    "projection": "Top-10",
    "ranking_overall": 9
  },
  "darian-mensah": {
    "name": "Darian Mensah",
    "position": "QB",
    "college": "Miami",
    "projection": "Top-10",
    "ranking_overall": 10
  },
  "trevor-goosby": {
    "name": "Trevor Goosby",
    "position": "OT",
    "college": "Texas",
    "projection": "Runde 1",
    "ranking_overall": 11
  },
  "cj-carr": {
    "name": "CJ Carr",
    "position": "QB",
    "college": "Notre Dame",
    "projection": "Runde 1",
    "ranking_overall": 12
  },
  "sammy-brown": {
    "name": "Sammy Brown",
    "position": "LB",
    "college": "Clemson",
    "projection": "Runde 1",
    "ranking_overall": 13
  },
  "lanorris-sellers": {
    "name": "LaNorris Sellers",
    "position": "QB",
    "college": "South Carolina",
    "projection": "Runde 1",
    "ranking_overall": 14
  },
  "matayo-uiagalelei": {
    "name": "Matayo Uiagalelei",
    "position": "EDGE",
    "college": "Oregon",
    "projection": "Runde 1",
    "ranking_overall": 15
  },
  "koi-perich": {
    "name": "Koi Perich",
    "position": "S",
    "college": "Oregon",
    "projection": "Runde 1",
    "ranking_overall": 16
  },
  "ellis-robinson-iv": {
    "name": "Ellis Robinson IV",
    "position": "CB",
    "college": "Georgia",
    "projection": "Runde 1",
    "ranking_overall": 17
  },
  "david-stone": {
    "name": "David Stone",
    "position": "DT",
    "college": "Oklahoma",
    "projection": "Runde 1",
    "ranking_overall": 18
  },
  "teitum-tuioti": {
    "name": "Teitum Tuioti",
    "position": "EDGE",
    "college": "Oregon",
    "projection": "Runde 1",
    "ranking_overall": 19
  },
  "carter-smith": {
    "name": "Carter Smith",
    "position": "OT",
    "college": "Indiana",
    "projection": "Runde 1",
    "ranking_overall": 20
  },
  "kewan-lacy": {
    "name": "Kewan Lacy",
    "position": "RB",
    "college": "Ole Miss",
    "projection": "Runde 1",
    "ranking_overall": 21
  },
  "ryan-williams": {
    "name": "Ryan Williams",
    "position": "WR",
    "college": "Alabama",
    "projection": "Runde 1",
    "ranking_overall": 22
  },
  "jamari-johnson": {
    "name": "Jamari Johnson",
    "position": "TE",
    "college": "Oregon",
    "projection": "Runde 1",
    "ranking_overall": 23
  },
  "kj-duff": {
    "name": "KJ Duff",
    "position": "WR",
    "college": "Rutgers",
    "projection": "Runde 1",
    "ranking_overall": 24
  },
  "nick-marsh": {
    "name": "Nick Marsh",
    "position": "WR",
    "college": "Indiana",
    "projection": "Runde 1",
    "ranking_overall": 25
  },
  "ahmad-hardy": {
    "name": "Ahmad Hardy",
    "position": "RB",
    "college": "Missouri",
    "projection": "Runde 1",
    "ranking_overall": 26
  },
  "charlie-becker": {
    "name": "Charlie Becker",
    "position": "WR",
    "college": "Indiana",
    "projection": "Runde 1",
    "ranking_overall": 27
  },
  "brandon-baker": {
    "name": "Brandon Baker",
    "position": "OT",
    "college": "Texas",
    "projection": "Runde 1",
    "ranking_overall": 28
  },
  "dylan-raiola": {
    "name": "Dylan Raiola",
    "position": "QB",
    "college": "Nebraska",
    "projection": "Runde 2",
    "ranking_overall": 29
  },
  "kj-bolden": {
    "name": "KJ Bolden",
    "position": "S",
    "college": "Georgia",
    "projection": "Runde 1",
    "ranking_overall": 30
  },
  "tae-johnson": {
    "name": "Tae Johnson",
    "position": "S",
    "college": "Notre Dame",
    "projection": "Runde 1",
    "ranking_overall": 31
  },
  "drew-mestemaker": {
    "name": "Drew Mestemaker",
    "position": "QB",
    "college": "Oklahoma State",
    "projection": "Runde 1",
    "ranking_overall": 32
  },
  "jayden-maiava": {
    "name": "Jayden Maiava",
    "position": "QB",
    "college": "USC",
    "projection": "Runde 1-2",
    "ranking_overall": 33
  },
  "ahmad-moten-sr": {
    "name": "Ahmad Moten Sr.",
    "position": "DT",
    "college": "Miami",
    "projection": "Runde 1-2",
    "ranking_overall": 34
  },
  "zabien-brown": {
    "name": "Zabien Brown",
    "position": "CB",
    "college": "Alabama",
    "projection": "Runde 1-2",
    "ranking_overall": 35
  },
  "kelley-jones": {
    "name": "Kelley Jones",
    "position": "CB",
    "college": "Mississippi State",
    "projection": "Runde 1-2",
    "ranking_overall": 36
  },
  "treydez-green": {
    "name": "Trey'Dez Green",
    "position": "TE",
    "college": "LSU",
    "projection": "Runde 1-2",
    "ranking_overall": 37
  },
  "kyngstonn-viliamu-asa": {
    "name": "Kyngstonn Viliamu-Asa",
    "position": "LB",
    "college": "Notre Dame",
    "projection": "Runde 1-2",
    "ranking_overall": 38
  },
  "damon-wilson-ii": {
    "name": "Damon Wilson II",
    "position": "EDGE",
    "college": "Missouri",
    "projection": "Runde 2",
    "ranking_overall": 39
  },
  "yhonzae-pierre": {
    "name": "Yhonzae Pierre",
    "position": "EDGE",
    "college": "Alabama",
    "projection": "Runde 2",
    "ranking_overall": 40
  },
  "quincy-rhodes-jr": {
    "name": "Quincy Rhodes Jr.",
    "position": "EDGE",
    "college": "Arkansas",
    "projection": "Runde 2",
    "ranking_overall": 41
  },
  "amauri-washington": {
    "name": "A'Mauri Washington",
    "position": "DT",
    "college": "Oregon",
    "projection": "Runde 2",
    "ranking_overall": 42
  },
  "ryan-wingo": {
    "name": "Ryan Wingo",
    "position": "WR",
    "college": "Texas",
    "projection": "Runde 2",
    "ranking_overall": 43
  },
  "jadan-baugh": {
    "name": "Jadan Baugh",
    "position": "RB",
    "college": "Florida",
    "projection": "Runde 2",
    "ranking_overall": 44
  },
  "will-echoles": {
    "name": "Will Echoles",
    "position": "DT",
    "college": "Ole Miss",
    "projection": "Runde 2",
    "ranking_overall": 45
  },
  "aj-holmes-jr": {
    "name": "A.J. Holmes Jr.",
    "position": "DT",
    "college": "Texas Tech",
    "projection": "Runde 2",
    "ranking_overall": 46
  },
  "iapani-laloulu": {
    "name": "Iapani Laloulu",
    "position": "IOL",
    "college": "Oregon",
    "projection": "Runde 2",
    "ranking_overall": 47
  },
  "ashton-hampton": {
    "name": "Ashton Hampton",
    "position": "CB",
    "college": "Clemson",
    "projection": "Runde 2",
    "ranking_overall": 48
  },
  "rasheem-biles": {
    "name": "Rasheem Biles",
    "position": "LB",
    "college": "Texas",
    "projection": "Runde 2",
    "ranking_overall": 49
  },
  "ben-roberts": {
    "name": "Ben Roberts",
    "position": "LB",
    "college": "Texas Tech",
    "projection": "Runde 2",
    "ranking_overall": 50
  },
  "dj-lagway": {
    "name": "DJ Lagway",
    "position": "QB",
    "college": "Florida",
    "projection": "Runde 2",
    "ranking_overall": 51
  },
  "kaliq-lockett": {
    "name": "Kaliq Lockett",
    "position": "WR",
    "college": "Texas",
    "projection": "Runde 2",
    "ranking_overall": 52
  },
  "justus-terry": {
    "name": "Justus Terry",
    "position": "DT",
    "college": "Texas",
    "projection": "Runde 2",
    "ranking_overall": 53
  },
  "nate-frazier": {
    "name": "Nate Frazier",
    "position": "RB",
    "college": "Georgia",
    "projection": "Runde 2-3",
    "ranking_overall": 54
  },
  "williams-nwaneri": {
    "name": "Williams Nwaneri",
    "position": "EDGE",
    "college": "Missouri",
    "projection": "Runde 3",
    "ranking_overall": 55
  },
  "peyton-woodyard": {
    "name": "Peyton Woodyard",
    "position": "S",
    "college": "Georgia",
    "projection": "Runde 3",
    "ranking_overall": 56
  },
  "vernell-brown-iii": {
    "name": "Vernell Brown III",
    "position": "WR",
    "college": "Florida",
    "projection": "Runde 3",
    "ranking_overall": 57
  },
  "jermod-mccoy": {
    "name": "Jermod McCoy",
    "position": "CB",
    "college": "Tennessee",
    "projection": "Day 2",
    "ranking_overall": 58
  },
  "nyckoles-harbor": {
    "name": "Nyckoles Harbor",
    "position": "WR",
    "college": "South Carolina",
    "projection": "Day 3",
    "ranking_overall": 59
  },
  "olaivavega-ioane": {
    "name": "Olaivavega Ioane",
    "position": "IOL",
    "college": "Penn State",
    "projection": "Day 2",
    "ranking_overall": 60
  },
  "kenyon-sadiq": {
    "name": "Kenyon Sadiq",
    "position": "TE",
    "college": "Oregon",
    "projection": "Day 2",
    "ranking_overall": 61
  }
}